{
  "audiovisual_files": {
    "fbc80e2e-244f-428d-b7d0-9d321688ac1e": {
      "label": "Fontaine Saint Blaise 360 Video Part 2",
      "is_offline": false,
      "file_type": "Video",
      "file_url": "https://aviary-p-ualberta.s3.wasabisys.com/collection_resource_files/resource_files/000/262/591/original/001_FontaineSaintBlaise_Blaise02.mp4?1739382238",
      "duration": 28
    }
  },
  "auto_generate_web_page": true,
  "label": "Annotation of Fontaine Saint Blaise 360 Video - Part 2",
  "description": [
    {
      "type": "paragraph",
      "children": [
        {
          "text": "Part 2 of Fontaine Saint Blaise 360 Video"
        }
      ]
    }
  ],
  "created_at": "2025-07-07T23:20:15.213Z",
  "created_by": "ndamours14",
  "updated_at": "2025-07-07T23:20:15.213Z",
  "updated_by": "ndamours14"
}